wrapspawner/__init__.py
wrapspawner/wrapspawner.py
wrapspawner-1.0.1.dist-info/LICENSE
wrapspawner-1.0.1.dist-info/METADATA
wrapspawner-1.0.1.dist-info/WHEEL
wrapspawner-1.0.1.dist-info/top_level.txt
wrapspawner-1.0.1.dist-info/RECORD
